Metadata-Version: 2.1
Name: makeflaskreact
Version: 0.0.1
Summary: To make it easier to create a quick flask react app
Home-page: https://github.com/greysonevins/makeflaskreact
Author: Greyson Nevins-Archer
Author-email: greyson.nevins@gmail.com
License: MIT
Platform: UNKNOWN
Classifier: Programming Language :: Python :: 3
Classifier: Operating System :: OS Independent
Requires-Python: >=3.6
